pyCTT/__init__.py
pyCTT/consts.py
pyCTT/items.py
pyCTT/scrapper.py
pyCTT-1.0.0.dist-info/LICENSE
pyCTT-1.0.0.dist-info/METADATA
pyCTT-1.0.0.dist-info/WHEEL
pyCTT-1.0.0.dist-info/top_level.txt
pyCTT-1.0.0.dist-info/zip-safe
pyCTT-1.0.0.dist-info/RECORD
