Metadata-Version: 2.1
Name: pyCTT
Version: 1.0.0
Summary: Python library to retrieve package information from CTT
Home-page: https://github.com/dpjrodrigues/pyCTT
Author: Diogo Rodrigues
Author-email: dpjrodrigues@gmail.com
License: MIT License
Platform: any
Classifier: License :: OSI Approved :: MIT License
Classifier: Intended Audience :: Developers
Classifier: Operating System :: OS Independent
Classifier: Programming Language :: Python
Classifier: Programming Language :: Python :: 3
Classifier: Topic :: Software Development :: Libraries :: Python Modules
Requires-Dist: aiohttp
Requires-Dist: lxml
